README.md
setup.py
sweet.db.egg-info/PKG-INFO
sweet.db.egg-info/SOURCES.txt
sweet.db.egg-info/dependency_links.txt
sweet.db.egg-info/requires.txt
sweet.db.egg-info/top_level.txt
sweet/modules/db.py